snowmobile/__init__.py
snowmobile/__main__.py
snowmobile/snowconn.py
snowmobile/snowcreds.py
snowmobile/snowloader.py
snowmobile/snowprocess.py
snowmobile/snowquery.py
snowmobile/snowscripter.py
snowmobile-0.1.13.dist-info/AUTHORS.rst
snowmobile-0.1.13.dist-info/LICENSE.txt
snowmobile-0.1.13.dist-info/METADATA
snowmobile-0.1.13.dist-info/WHEEL
snowmobile-0.1.13.dist-info/entry_points.txt
snowmobile-0.1.13.dist-info/top_level.txt
snowmobile-0.1.13.dist-info/RECORD
