Metadata-Version: 2.1
Name: snowmobile
Version: 0.1.13
Summary: A simple set of modules for streamlined interaction with the Snowflake Database
Home-page: https://github.com/GEM7318/Snowmobile
Author: Grant Murray
Author-email: gmurray203@gmail.com
License: MIT
Project-URL: Documentation, https://snowmobile.readthedocs.io/en/latest/index.html
Platform: any
Classifier: License :: OSI Approved :: MIT License
Classifier: Programming Language :: Python :: 3.7
Classifier: Programming Language :: Python :: 3.8
Requires-Python: >=3.7.
Requires-Dist: pandas
Requires-Dist: snowflake-connector-python
Requires-Dist: sqlparse
Requires-Dist: fcache
Requires-Dist: ipython
Provides-Extra: testing
Requires-Dist: pytest ; extra == 'testing'
Requires-Dist: pytest-cov ; extra == 'testing'
